{
   "response":[
      {
         "list":[
            {
               "name":"Nicobars",
               "zone":"green"
            },
            {
               "name":"North And Middle Andaman",
               "zone":"green"
            },
            {
               "name":"South Andamans",
               "zone":"red"
            }
         ],
         "state":"Andaman And Nicobar lslands"
      },
      {
         "list":[
            {
               "name":"Vizianagaram",
               "zone":"green"
            },
            {
               "name":"Anantapur",
               "zone":"orange"
            },
            {
               "name":"East Godavari",
               "zone":"orange"
            },
            {
               "name":"Prakasam",
               "zone":"orange"
            },
            {
               "name":"Srikakulam",
               "zone":"orange"
            },
            {
               "name":"Visakhapatanam",
               "zone":"orange"
            },
            {
               "name":"West Godavari",
               "zone":"orange"
            },
            {
               "name":"Y.S.R.",
               "zone":"orange"
            },
            {
               "name":"Chittoor",
               "zone":"red"
            },
            {
               "name":"Guntur",
               "zone":"red"
            },
            {
               "name":"Krishna",
               "zone":"red"
            },
            {
               "name":"Kurnool",
               "zone":"red"
            },
            {
               "name":"Spsr Nellore",
               "zone":"red"
            }
         ],
         "state":"Andhra Pradesh"
      },
      {
         "list":[
            {
               "name":"Anjaw",
               "zone":"green"
            },
            {
               "name":"Changlang",
               "zone":"green"
            },
            {
               "name":"Dibang Valley",
               "zone":"green"
            },
            {
               "name":"East Kameng",
               "zone":"green"
            },
            {
               "name":"East Slang",
               "zone":"green"
            },
            {
               "name":"Kamle",
               "zone":"green"
            },
            {
               "name":"Kra Daadi",
               "zone":"green"
            },
            {
               "name":"KurungKumey",
               "zone":"green"
            },
            {
               "name":"Lepa rada",
               "zone":"green"
            },
            {
               "name":"Lohit",
               "zone":"green"
            },
            {
               "name":"Longding",
               "zone":"green"
            },
            {
               "name":"Lower Dibang Valley",
               "zone":"green"
            },
            {
               "name":"Lower Siang",
               "zone":"green"
            },
            {
               "name":"Lower Subansiri",
               "zone":"green"
            },
            {
               "name":"Namsai",
               "zone":"green"
            },
            {
               "name":"PakkeKessang",
               "zone":"green"
            },
            {
               "name":"Papum Pare",
               "zone":"green"
            },
            {
               "name":"Shi Yomi",
               "zone":"green"
            },
            {
               "name":"Siang",
               "zone":"green"
            },
            {
               "name":"Tawang",
               "zone":"green"
            },
            {
               "name":"Tirap",
               "zone":"green"
            },
            {
               "name":"Upper Siang",
               "zone":"green"
            },
            {
               "name":"Upper Subansiri",
               "zone":"green"
            },
            {
               "name":"West Kameng",
               "zone":"green"
            },
            {
               "name":"West Siang",
               "zone":"green"
            }
         ],
         "state":"Arunachal Pradesh"
      },
      {
         "list":[
            {
               "name":"Baksa",
               "zone":"green"
            },
            {
               "name":"Barpeta",
               "zone":"green"
            },
            {
               "name":"Biswanath",
               "zone":"green"
            },
            {
               "name":"Bongaigaon",
               "zone":"green"
            },
            {
               "name":"Cachar",
               "zone":"green"
            },
            {
               "name":"Charaideo",
               "zone":"green"
            },
            {
               "name":"Chirang",
               "zone":"green"
            },
            {
               "name":"Da rra ng",
               "zone":"green"
            },
            {
               "name":"Dhemaji",
               "zone":"green"
            },
            {
               "name":"Dibrugarh",
               "zone":"green"
            },
            {
               "name":"Dima Hasao",
               "zone":"green"
            },
            {
               "name":"Golaghat",
               "zone":"green"
            },
            {
               "name":"Hailakandi",
               "zone":"green"
            },
            {
               "name":"Hojai",
               "zone":"green"
            },
            {
               "name":"Jorhat",
               "zone":"green"
            },
            {
               "name":"Kamrup",
               "zone":"green"
            },
            {
               "name":"Kamrup Metro",
               "zone":"green"
            },
            {
               "name":"KarbiAnglong",
               "zone":"green"
            },
            {
               "name":"Karimganj",
               "zone":"green"
            },
            {
               "name":"Kokrajhar",
               "zone":"green"
            },
            {
               "name":"Lakhimpur",
               "zone":"green"
            },
            {
               "name":"Majuli",
               "zone":"green"
            },
            {
               "name":"Nagaon",
               "zone":"green"
            },
            {
               "name":"Nalbari",
               "zone":"green"
            },
            {
               "name":"Sivasagar",
               "zone":"green"
            },
            {
               "name":"Sonitpur",
               "zone":"green"
            },
            {
               "name":"South Salmara Mancachar",
               "zone":"green"
            },
            {
               "name":"Tinsukia",
               "zone":"green"
            },
            {
               "name":"Udalguri",
               "zone":"green"
            },
            {
               "name":"West KarbiAnglong",
               "zone":"green"
            },
            {
               "name":"Dhubri",
               "zone":"orange"
            },
            {
               "name":"Goalpara",
               "zone":"orange"
            },
            {
               "name":"Marigaon",
               "zone":"orange"
            }
         ],
         "state":"Assam"
      },
      {
         "list":[
            {
               "name":"Araria",
               "zone":"green"
            },
            {
               "name":"Jamui",
               "zone":"green"
            },
            {
               "name":"Katihar",
               "zone":"green"
            },
            {
               "name":"Khagaria",
               "zone":"green"
            },
            {
               "name":"Kishanganj",
               "zone":"green"
            },
            {
               "name":"Muzaffarpur",
               "zone":"green"
            },
            {
               "name":"PashchimChampran",
               "zone":"green"
            },
            {
               "name":"Sa ha rsa",
               "zone":"green"
            },
            {
               "name":"Samastipur",
               "zone":"green"
            },
            {
               "name":"Sheikhpura",
               "zone":"green"
            },
            {
               "name":"Sheohar",
               "zone":"green"
            },
            {
               "name":"Sitamarhi",
               "zone":"green"
            },
            {
               "name":"Supaul",
               "zone":"green"
            },
            {
               "name":"Arwal",
               "zone":"orange"
            },
            {
               "name":"Aurangabad",
               "zone":"orange"
            },
            {
               "name":"Banka",
               "zone":"orange"
            },
            {
               "name":"Begusarai",
               "zone":"orange"
            },
            {
               "name":"Bhagalpur",
               "zone":"orange"
            },
            {
               "name":"Bhojpur",
               "zone":"orange"
            },
            {
               "name":"Darbhanga",
               "zone":"orange"
            },
            {
               "name":"Gopalganj",
               "zone":"orange"
            },
            {
               "name":"Jehanabad",
               "zone":"orange"
            },
            {
               "name":"Kaimur (Bhabua)",
               "zone":"orange"
            },
            {
               "name":"La khisa rai",
               "zone":"orange"
            },
            {
               "name":"Madhepura",
               "zone":"orange"
            },
            {
               "name":"Madhubani",
               "zone":"orange"
            },
            {
               "name":"Nalanda",
               "zone":"orange"
            },
            {
               "name":"Nawada",
               "zone":"orange"
            },
            {
               "name":"PurbiChamparan",
               "zone":"orange"
            },
            {
               "name":"Purnia",
               "zone":"orange"
            },
            {
               "name":"Saran",
               "zone":"orange"
            },
            {
               "name":"Siwan",
               "zone":"orange"
            },
            {
               "name":"Vaishali",
               "zone":"orange"
            },
            {
               "name":"Buxar",
               "zone":"red"
            },
            {
               "name":"Gaya",
               "zone":"red"
            },
            {
               "name":"Munger",
               "zone":"red"
            },
            {
               "name":"Patna",
               "zone":"red"
            },
            {
               "name":"Rohtas",
               "zone":"red"
            }
         ],
         "state":"Bihar"
      },
      {
         "list":[
            {
               "name":"Chandigarh",
               "zone":"red"
            }
         ],
         "state":"Chandigarh"
      },
      {
         "list":[
            {
               "name":"Balod",
               "zone":"green"
            },
            {
               "name":"Baloda Bazar",
               "zone":"green"
            },
            {
               "name":"Balrampur",
               "zone":"green"
            },
            {
               "name":"Bastar",
               "zone":"green"
            },
            {
               "name":"Bemetara",
               "zone":"green"
            },
            {
               "name":"Bijapur",
               "zone":"green"
            },
            {
               "name":"Bilaspur",
               "zone":"green"
            },
            {
               "name":"Dantewada",
               "zone":"green"
            },
            {
               "name":"Dhamtari",
               "zone":"green"
            },
            {
               "name":"Durg",
               "zone":"green"
            },
            {
               "name":"Garivaband",
               "zone":"green"
            },
            {
               "name":"Janjgir-Champa",
               "zone":"green"
            },
            {
               "name":"Jashpur",
               "zone":"green"
            },
            {
               "name":"Kabirdham",
               "zone":"green"
            },
            {
               "name":"Kanker",
               "zone":"green"
            },
            {
               "name":"Kondagaon",
               "zone":"green"
            },
            {
               "name":"Korea",
               "zone":"green"
            },
            {
               "name":"Mahasamund",
               "zone":"green"
            },
            {
               "name":"Munseli",
               "zone":"green"
            },
            {
               "name":"Na rayan pur",
               "zone":"green"
            },
            {
               "name":"Raigarh",
               "zone":"green"
            },
            {
               "name":"Rajnandgaon",
               "zone":"green"
            },
            {
               "name":"Sukma",
               "zone":"green"
            },
            {
               "name":"Surajpur",
               "zone":"green"
            },
            {
               "name":"Surguia",
               "zone":"green"
            },
            {
               "name":"Korba",
               "zone":"orange"
            },
            {
               "name":"Raipur",
               "zone":"red"
            }
         ],
         "state":"Chhattisgarh"
      }
   ]
}
